tests/__init__.py
tests/test_RBFInterpolator.py
tests/test_jitCompile.py
torchrbf/RBFInterpolator.py
torchrbf/__init__.py
torchrbf/radial_fn.py
torchrbf/test_RBFInterpolator.py
torchrbf/test_grad.py
torchrbf/test_kernel.py
torchrbf-1.0.0.dist-info/licenses/LICENSE
torchrbf-1.0.0.dist-info/METADATA
torchrbf-1.0.0.dist-info/WHEEL
torchrbf-1.0.0.dist-info/top_level.txt
torchrbf-1.0.0.dist-info/RECORD
