Metadata-Version: 2.4
Name: torchrbf
Version: 1.0.0
Summary: Radial Basis Function Interpolation in PyTorch
Author: Arman Maesumi
Author-email: arman.maesumi@gmail.com
Keywords: python,pytorch,rbf,interpolation,radial basis function
License-File: LICENSE
Dynamic: author
Dynamic: author-email
Dynamic: description
Dynamic: description-content-type
Dynamic: keywords
Dynamic: license-file
Dynamic: summary
